upstox_lib/__init__.py
upstox_lib/py.typed
upstox_lib/upstoxLib.py
upstox_lib-0.1.0.dist-info/METADATA
upstox_lib-0.1.0.dist-info/WHEEL
upstox_lib-0.1.0.dist-info/RECORD
