Metadata-Version: 2.4
Name: upstox-lib
Version: 0.1.0
Summary: Add your description here
Author-email: deepanshu mangolia <deepanshu.mangolia@rmoneyindia.in>
Requires-Python: >=3.12
Requires-Dist: pandas>=2.3.0
Requires-Dist: requests>=2.32.4
